Furhat_client-0.1.dist-info/METADATA
Furhat_client-0.1.dist-info/RECORD
Furhat_client-0.1.dist-info/WHEEL
Furhat_client-0.1.dist-info/top_level.txt
furhat/__init__.py
furhat/connect_to_iristk.py
furhat/iristk_client.py
