Metadata-Version: 2.1
Name: Furhat-client
Version: 0.1
Summary: Python Furhat client library
Home-page: UNKNOWN
Author: Patrik Jonell
Author-email: me@patrikjonell.se
License: UNKNOWN
Platform: UNKNOWN
